phlocation/__init__.py
phlocation/admin.py
phlocation/apps.py
phlocation/forms.py
phlocation/models.py
phlocation/serializers.py
phlocation/tests.py
phlocation/urls.py
phlocation/views.py
phlocation/migrations/0001_initial.py
phlocation/migrations/__init__.py
phlocation2-0.0.1.dist-info/LICENCE.txt
phlocation2-0.0.1.dist-info/METADATA
phlocation2-0.0.1.dist-info/WHEEL
phlocation2-0.0.1.dist-info/top_level.txt
phlocation2-0.0.1.dist-info/RECORD
